{
  "meta": {
    "schema_version": 2,
    "source_url": "https://api.coingecko.com/api/v3/simple/price",
    "fetched_at_utc": "2026-03-18 06:03:44 UTC",
    "fetched_at_ist": "2026-03-18 11:33:44 IST",
    "asset_count": 4,
    "content_hash": "62a26fa50d19193e745655fb4e3c0ac4d3554e6a5d24f9044aba3fbda595ca86",
    "previous_hash": "5569541171dcaa9ba49fd791d03c8dba910e2ed52902ba1f1926d8d62f8d5bb2",
    "assets_changed_vs_previous": 4,
    "largest_move_asset": "ethereum",
    "largest_move_24h": 0.8088
  },
  "assets": {
    "bitcoin": {
      "price_usd": 73993.0,
      "change_24h": 0.0915753086740798
    },
    "ethereum": {
      "price_usd": 2319.87,
      "change_24h": 0.8087613240233329
    },
    "solana": {
      "price_usd": 93.97,
      "change_24h": 0.16938283308201182
    },
    "bnb": {
      "price_usd": 671.73,
      "change_24h": -0.32608979847841824
    }
  }
}