{
  "schema_version": 2,
  "date_ist": "2026-06-11",
  "target_commits_per_day": 100,
  "commits_today": 2,
  "remaining_today": 98,
  "status": "on-track",
  "streak_days": 70,
  "commit_count_source": "git-history",
  "pending_commit_included": 1,
  "last_commit_utc": "2026-06-10 19:11:36 UTC",
  "last_commit_ist": "2026-06-11 00:41:36 IST",
  "last_data_update_utc": "2026-06-10 21:28:21 UTC",
  "last_data_update_ist": "2026-06-11 02:58:21 IST",
  "sources": {
    "github": {
      "label": "GitHub Trending",
      "item_count": 16,
      "last_fetch_utc": "2026-06-09 00:12:43 UTC",
      "last_fetch_ist": "2026-06-09 05:42:43 IST",
      "content_hash": "84c12ed21757db1a51f69b70ddce9666af4f50a868ca3f206c62537eaf7538e6",
      "content_hash_short": "84c12ed21757",
      "change_flag": true,
      "change_summary": "+10 new repos"
    },
    "hacker_news": {
      "label": "Hacker News",
      "item_count": 5,
      "last_fetch_utc": "2026-06-09 11:39:13 UTC",
      "last_fetch_ist": "2026-06-09 17:09:13 IST",
      "content_hash": "72c52677728ca5e066a21fe21630de68c83a49b700d1852e233532789be1ee35",
      "content_hash_short": "72c52677728c",
      "change_flag": true,
      "change_summary": "+5 new stories"
    },
    "crypto": {
      "label": "Crypto",
      "item_count": 4,
      "last_fetch_utc": "2026-06-10 21:28:21 UTC",
      "last_fetch_ist": "2026-06-11 02:58:21 IST",
      "content_hash": "0a80983b03a9036028fc0e9a3ba87cb5a6457d28bd87d54a4f39307fe4597fe0",
      "content_hash_short": "0a80983b03a9",
      "change_flag": true,
      "change_summary": "4 assets moved"
    }
  }
}