{
  "schema_version": 2,
  "date_ist": "2026-05-13",
  "target_commits_per_day": 100,
  "commits_today": 4,
  "remaining_today": 96,
  "status": "on-track",
  "streak_days": 54,
  "commit_count_source": "git-history",
  "pending_commit_included": 1,
  "last_commit_utc": "2026-05-12 22:35:24 UTC",
  "last_commit_ist": "2026-05-13 04:05:24 IST",
  "last_data_update_utc": "2026-05-12 23:41:42 UTC",
  "last_data_update_ist": "2026-05-13 05:11:42 IST",
  "sources": {
    "github": {
      "label": "GitHub Trending",
      "item_count": 13,
      "last_fetch_utc": "2026-05-11 12:11:39 UTC",
      "last_fetch_ist": "2026-05-11 17:41:39 IST",
      "content_hash": "281f35151e38c300d44597f3f79fb1b6a1e7d8cb5852c59bc822fc63718dddc5",
      "content_hash_short": "281f35151e38",
      "change_flag": true,
      "change_summary": "+8 new repos"
    },
    "hacker_news": {
      "label": "Hacker News",
      "item_count": 5,
      "last_fetch_utc": "2026-05-12 23:41:42 UTC",
      "last_fetch_ist": "2026-05-13 05:11:42 IST",
      "content_hash": "dab5a832f586b17957b5244bf16f8d061e27ee1ee204e00804d6b41a82c5aef0",
      "content_hash_short": "dab5a832f586",
      "change_flag": true,
      "change_summary": "+1 new stories"
    },
    "crypto": {
      "label": "Crypto",
      "item_count": 4,
      "last_fetch_utc": "2026-05-12 19:22:03 UTC",
      "last_fetch_ist": "2026-05-13 00:52:03 IST",
      "content_hash": "5524141ccfa85d06382c10f00c5771d80a24d03e87db932934a64d1d8839fd2d",
      "content_hash_short": "5524141ccfa8",
      "change_flag": true,
      "change_summary": "4 assets moved"
    }
  }
}