{
  "schema_version": 2,
  "date_ist": "2026-03-29",
  "target_commits_per_day": 100,
  "commits_today": 24,
  "remaining_today": 76,
  "status": "on-track",
  "streak_days": 36,
  "commit_count_source": "git-history",
  "pending_commit_included": 1,
  "last_commit_utc": "2026-03-29 14:53:23 UTC",
  "last_commit_ist": "2026-03-29 20:23:23 IST",
  "last_data_update_utc": "2026-03-29 15:34:40 UTC",
  "last_data_update_ist": "2026-03-29 21:04:40 IST",
  "sources": {
    "github": {
      "label": "GitHub Trending",
      "item_count": 12,
      "last_fetch_utc": "2026-03-29 12:01:53 UTC",
      "last_fetch_ist": "2026-03-29 17:31:53 IST",
      "content_hash": "9754dd30916815c08f2dba3c0ae60ae35f2ad92dce107c125a5662609df59c0e",
      "content_hash_short": "9754dd309168",
      "change_flag": true,
      "change_summary": "+9 new repos"
    },
    "hacker_news": {
      "label": "Hacker News",
      "item_count": 5,
      "last_fetch_utc": "2026-03-29 15:34:40 UTC",
      "last_fetch_ist": "2026-03-29 21:04:40 IST",
      "content_hash": "0694205b820f526c8ae8cffcf9933720a0f8065fbf72e41d9ecad10a60153346",
      "content_hash_short": "0694205b820f",
      "change_flag": true,
      "change_summary": "+2 new stories"
    },
    "crypto": {
      "label": "Crypto",
      "item_count": 4,
      "last_fetch_utc": "2026-03-29 13:20:17 UTC",
      "last_fetch_ist": "2026-03-29 18:50:17 IST",
      "content_hash": "5cb50371079e3c6b013c904f0d66d04e0b0c631c92a93c1238971000e052f4dc",
      "content_hash_short": "5cb50371079e",
      "change_flag": true,
      "change_summary": "4 assets moved"
    }
  }
}